jaai_hub/__init__.py
jaai_hub/streaming_message.py
jaai_hub/custom_api/__init__.py
jaai_hub/custom_api/base.py
jaai_hub/custom_api/openai_compat.py
jaai_hub-1.2.0.dist-info/METADATA
jaai_hub-1.2.0.dist-info/WHEEL
jaai_hub-1.2.0.dist-info/RECORD
