Metadata-Version: 2.4
Name: jaai-hub
Version: 1.2.0
Summary: Main hub package for JAAI Hub utilities and components
Author: JAAI Team
License: Proprietary
Keywords: ai,api,chat,langchain,openai,streaming
Classifier: Development Status :: 4 - Beta
Classifier: Intended Audience :: Developers
Classifier: License :: Other/Proprietary License
Classifier: Programming Language :: Python :: 3
Classifier: Programming Language :: Python :: 3.11
Classifier: Programming Language :: Python :: 3.12
Classifier: Topic :: Communications :: Chat
Classifier: Topic :: Scientific/Engineering :: Artificial Intelligence
Classifier: Topic :: Software Development :: Libraries :: Python Modules
Requires-Python: >=3.11
Requires-Dist: langchain-community>=0.0.10
Requires-Dist: langchain-core>=0.1.0
Requires-Dist: langchain-openai>=0.0.1
Requires-Dist: loguru>=0.7.0
Requires-Dist: markdownify>=0.11.0
Requires-Dist: pydantic>=2.4.0
Requires-Dist: requests>=2.25.0
Provides-Extra: dev
Requires-Dist: black>=23.0.0; extra == 'dev'
Requires-Dist: isort>=5.12.0; extra == 'dev'
Requires-Dist: pytest-asyncio>=0.21.0; extra == 'dev'
Requires-Dist: pytest>=7.0.0; extra == 'dev'
